{
  "collapse-filter": true,
  "search": "",
  "showTags": false,
  "showAttachments": false,
  "hideUnresolved": false,
  "showOrphans": true,
  "collapse-color-groups": false,
  "colorGroups": [
    {
      "query": "path:Data",
      "color": {
        "a": 1,
        "rgb": 5431425
      }
    },
    {
      "query": "path:Classification",
      "color": {
        "a": 1,
        "rgb": 14725458
      }
    },
    {
      "query": "path:Languages",
      "color": {
        "a": 1,
        "rgb": 14701276
      }
    },
    {
      "query": "path:Prediction",
      "color": {
        "a": 1,
        "rgb": 5401056
      }
    },
    {
      "query": "path:Semantic-Similarity",
      "color": {
        "a": 1,
        "rgb": 14701138
      }
    },
    {
      "query": "path:/",
      "color": {
        "a": 1,
        "rgb": 2783839
      }
    }
  ],
  "collapse-display": false,
  "showArrow": true,
  "textFadeMultiplier": -0.4,
  "nodeSizeMultiplier": 1.29299287410926,
  "lineSizeMultiplier": 2.08202247191011,
  "collapse-forces": false,
  "centerStrength": 0.81353919239905,
  "repelStrength": 12.375296912114,
  "linkStrength": 0.371733966745843,
  "linkDistance": 345,
  "scale": 0.836038660166996,
  "close": true
}